proofly/__init__.py
proofly/analyzer.py
proofly/config.py
proofly/enums.py
proofly/exceptions.py
proofly/export.py
proofly/models.py
proofly-1.2.4.dist-info/LICENSE
proofly-1.2.4.dist-info/METADATA
proofly-1.2.4.dist-info/WHEEL
proofly-1.2.4.dist-info/top_level.txt
proofly-1.2.4.dist-info/RECORD
