Metadata-Version: 2.1
Name: proofly
Version: 1.2.4
Summary: Enterprise-grade health metrics analysis and prediction engine
Author: Mohammed Ufraan
Author-email: Mohammed Ufraan <kurosen930@gmail.com>
License: Proofly - A health tracking and management application designed to generate professional invoices, bills, and receipts while managing user health data securely.
Project-URL: Homepage, https://github.com/moroii69/proofly
Keywords: health,analytics,medical,prediction
Classifier: License :: OSI Approved :: MIT License
Classifier: Programming Language :: Python
Classifier: Programming Language :: Python :: 3
Classifier: Programming Language :: Python :: 3.8
Classifier: Programming Language :: Python :: 3.9
Classifier: Programming Language :: Python :: 3.10
Requires-Python: >=3.8
License-File: LICENSE
Requires-Dist: dataclasses
Requires-Dist: typing
Requires-Dist: datetime
Provides-Extra: dev
Requires-Dist: pytest; extra == "dev"
